glpi_provider/__init__.py
glpi_provider/settings.py
glpi_provider/decorators/__init__.py
glpi_provider/decorators/session.py
glpi_provider/models/__init__.py
glpi_provider/models/entity.py
glpi_provider/models/location.py
glpi_provider/models/ticket.py
glpi_provider/models/user.py
glpi_provider/providers/__init__.py
glpi_provider/providers/glpi_provider.py
glpi_provider/services/__init__.py
glpi_provider/services/glpi_service.py
glpi_provider/tests/__init__.py
glpi_provider/tests/test_entity_model.py
glpi_provider/tests/test_glpi_provider.py
glpi_provider/tests/test_location_model.py
glpi_provider/tests/test_ticket_model.py
glpi_provider/tests/test_url_transform.py
glpi_provider/tests/test_user_model.py
glpi_provider/tests/constants/__init__.py
glpi_provider/tests/constants/entities_responses.py
glpi_provider/tests/constants/locations_responses.py
glpi_provider/tests/constants/tickets_responses.py
glpi_provider/tests/constants/users_responses.py
glpi_provider/utils/__init__.py
glpi_provider/utils/url.py
glpi_provider-0.3.3.dist-info/LICENSE
glpi_provider-0.3.3.dist-info/METADATA
glpi_provider-0.3.3.dist-info/WHEEL
glpi_provider-0.3.3.dist-info/top_level.txt
glpi_provider-0.3.3.dist-info/RECORD
