Metadata-Version: 2.1
Name: glpi-provider
Version: 0.3.3
Summary: GLPI API Abstraction Layer
Author: Tatianno Alves
Author-email: tferreiraalves@gmail.com
License: MIT License
Keywords: glpi provider api rest
License-File: LICENSE
Requires-Dist: python-dotenv
Requires-Dist: requests
